setup.py
corexdiscrete/__init__.py
corexdiscrete/corex_discrete.py
corexdiscrete.egg-info/PKG-INFO
corexdiscrete.egg-info/SOURCES.txt
corexdiscrete.egg-info/dependency_links.txt
corexdiscrete.egg-info/entry_points.txt
corexdiscrete.egg-info/top_level.txt
corexdiscrete/corexdiscrete/__init__.py
corexdiscrete/corexdiscrete/corex.py
corexdiscrete/corexdiscrete/vis_corex.py