Metadata-Version: 1.1
Name: corexdiscrete
Version: 0.1.21
Summary: Corex finds latent factors that explain the most correlation in discrete data.
Home-page: https://github.com/brekelma/corexdiscrete
Author: Rob Brekelmans/Greg Ver Steeg
Author-email: brekelma@usc.edu
License: MIT
Download-URL: https://github.com/brekelma/corexdiscrete
Platform: UNKNOWN
Classifier: Programming Language :: Python
Classifier: Programming Language :: Python :: 3.5
